firefox_bookmark_extractor/__init__.py
firefox_bookmark_extractor/extractor.py
firefox_bookmark_extractor-1.0.0.dist-info/entry_points.txt
firefox_bookmark_extractor-1.0.0.dist-info/WHEEL
firefox_bookmark_extractor-1.0.0.dist-info/METADATA
firefox_bookmark_extractor-1.0.0.dist-info/RECORD
