Metadata-Version: 2.1
Name: firefox-bookmark-extractor
Version: 1.0.0
Summary: Firefox Bookmark Extractor can be used to extract urls from Firefox bookmarks. Scripts taps to Firefox's internal database and extracts data from required bookmark path.
Home-page: https://github.com/uuksu/firefox-bookmark-extractor
Author: Mikko Uuksulainen
Author-email: mikko.uuksulainen@uuksu.fi
Requires-Python: >=3.8,<4.0
Classifier: Programming Language :: Python :: 3
Classifier: Programming Language :: Python :: 3.8
Requires-Dist: argparse (>=1.4.0,<2.0.0)
Project-URL: Repository, https://github.com/uuksu/firefox-bookmark-extractor
